Workbook

Sheet キーワード一覧
A1: AWS 認定ソリューションアーキテクト – アソシエイト(SAA-C03)重要キーワード集
A2: 重要度:★★★=最頻出 / ★★=頻出 / ★=押さえておきたい。「理解度」列(黄色)はプルダウンで自分の習熟度を記録できます。
A4: No | B4: 分野 | C4: キーワード | D4: 概要 | E4: 試験での頻出ポイント | F4: 重要度 | G4: 理解度
A5: 1 | B5: コンピューティング | C5: Amazon EC2 | D5: 仮想サーバー。インスタンスタイプ(汎用/コンピューティング最適化/メモリ最適化/ストレージ最適化/高速コンピューティング)を選んで起動する | E5: ワークロードに合うインスタンスファミリーの選択 | F5: ★★★
A6: 2 | B6: コンピューティング | C6: オンデマンドインスタンス | D6: 秒/時間単位課金で長期契約なし | E6: 短期・予測不能・中断不可のワークロード | F6: ★★★
A7: 3 | B7: コンピューティング | C7: リザーブドインスタンス(RI) | D7: 1年/3年の利用を約束して大幅割引。スタンダードとコンバーティブルがある | E7: 常時稼働の安定ワークロードのコスト削減 | F7: ★★★
A8: 4 | B8: コンピューティング | C8: Savings Plans | D8: 1年/3年で時間あたりの利用額をコミットして割引。Compute Savings PlansはEC2・Fargate・Lambdaに適用 | E8: インスタンスタイプやリージョンを変える可能性がある場合はRIより柔軟 | F8: ★★★
A9: 5 | B9: コンピューティング | C9: スポットインスタンス | D9: AWSの余剰キャパシティを最大90%割引で利用。2分前通知で中断されうる | E9: 中断耐性のあるバッチ処理・ビッグデータ処理・CI。DBなど中断不可には不向き | F9: ★★★
A10: 6 | B10: コンピューティング | C10: Dedicated Hosts / Dedicated Instances | D10: 物理サーバーを専有。Dedicated Hostsはソケット・コア単位のライセンス持ち込み(BYOL)が可能 | E10: ライセンス要件・コンプライアンス要件があるとき | F10: ★★
A11: 7 | B11: コンピューティング | C11: プレイスメントグループ | D11: インスタンスの物理配置を制御。クラスター(低レイテンシ)、パーティション(Hadoop等の大規模分散)、スプレッド(障害分離・AZあたり最大7台) | E11: HPCはクラスター、重要少数インスタンスの分離はスプレッド | F11: ★★
A12: 8 | B12: コンピューティング | C12: EC2 Auto Scaling | D12: 需要に応じてインスタンス数を自動増減。起動テンプレート、ターゲット追跡/ステップ/スケジュール/予測スケーリング | E12: ヘルスチェックによる自動復旧、ELBとの組み合わせで高可用性 | F12: ★★★
A13: 9 | B13: コンピューティング | C13: 起動テンプレート | D13: AMI・インスタンスタイプ・SGなど起動設定のテンプレート。起動設定(Launch Configuration)の後継 | E13: バージョン管理可能。複数インスタンスタイプ・スポット混在に対応 | F13: ★
A14: 10 | B14: コンピューティング | C14: AMI | D14: EC2の起動イメージ。リージョン単位で、別リージョンへはコピーが必要 | E14: DRで別リージョンにAMIをコピー | F14: ★★
A15: 11 | B15: コンピューティング | C15: EC2インスタンスストア | D15: ホストに物理接続された一時ストレージ。停止・終了でデータ消失 | E15: 超高IOPSの一時データ・キャッシュ用。永続化が必要なら不可 | F15: ★★
A16: 12 | B16: コンピューティング | C16: AWS Lambda | D16: サーバーレスでコードを実行。最大実行時間15分、メモリ最大10GB、リクエスト単位課金 | E16: イベント駆動処理(S3アップロード等)。15分超の処理は不向き | F16: ★★★
... A235: 231 | B235: 設計原則 | C235: IaC(Infrastructure as Code) | D235: インフラの構成をコードで定義して自動構築する考え方。同じ環境を何度でも再現でき、バージョン管理・レビュー・ロールバックが容易になり、手作業のミスを減らせる | E235: 開発・検証・本番の環境差異をなくし、同じ構成を繰り返し構築したい | F235: ★★

Sheet 分野別集計
A1: 分野別キーワード数と学習進捗
A3: 分野 | B3: キーワード数 | C3: うち★★★ | D3: ◎ 説明できる | E3: ○ なんとなく | F3: △ 要復習 | G3: 習得率(◎の割合)
A4: コンピューティング | B4: =COUNTIF(キーワード一覧!$B$5:$B$235,A4) | C4: =COUNTIFS(キーワード一覧!$B$5:$B$235,A4,キーワード一覧!$F$5:$F$235,"★★★") | D4: =COUNTIFS(キーワード一覧!$B$5:$B$235,A4,キーワード一覧!$G$5:$G$235,"◎*") | E4: =COUNTIFS(キーワード一覧!$B$5:$B$235,A4,キーワード一覧!$G$5:$G$235,"○*") | F4: =COUNTIFS(キーワード一覧!$B$5:$B$235,A4,キーワード一覧!$G$5:$G$235,"△*") | G4: =IF(B4=0,0,D4/B4)
A5: ストレージ | B5: =COUNTIF(キーワード一覧!$B$5:$B$235,A5) | C5: =COUNTIFS(キーワード一覧!$B$5:$B$235,A5,キーワード一覧!$F$5:$F$235,"★★★") | D5: =COUNTIFS(キーワード一覧!$B$5:$B$235,A5,キーワード一覧!$G$5:$G$235,"◎*") | E5: =COUNTIFS(キーワード一覧!$B$5:$B$235,A5,キーワード一覧!$G$5:$G$235,"○*") | F5: =COUNTIFS(キーワード一覧!$B$5:$B$235,A5,キーワード一覧!$G$5:$G$235,"△*") | G5: =IF(B5=0,0,D5/B5)
A6: データベース | B6: =COUNTIF(キーワード一覧!$B$5:$B$235,A6) | C6: =COUNTIFS(キーワード一覧!$B$5:$B$235,A6,キーワード一覧!$F$5:$F$235,"★★★") | D6: =COUNTIFS(キーワード一覧!$B$5:$B$235,A6,キーワード一覧!$G$5:$G$235,"◎*") | E6: =COUNTIFS(キーワード一覧!$B$5:$B$235,A6,キーワード一覧!$G$5:$G$235,"○*") | F6: =COUNTIFS(キーワード一覧!$B$5:$B$235,A6,キーワード一覧!$G$5:$G$235,"△*") | G6: =IF(B6=0,0,D6/B6)
A7: ネットワーク | B7: =COUNTIF(キーワード一覧!$B$5:$B$235,A7) | C7: =COUNTIFS(キーワード一覧!$B$5:$B$235,A7,キーワード一覧!$F$5:$F$235,"★★★") | D7: =COUNTIFS(キーワード一覧!$B$5:$B$235,A7,キーワード一覧!$G$5:$G$235,"◎*") | E7: =COUNTIFS(キーワード一覧!$B$5:$B$235,A7,キーワード一覧!$G$5:$G$235,"○*") | F7: =COUNTIFS(キーワード一覧!$B$5:$B$235,A7,キーワード一覧!$G$5:$G$235,"△*") | G7: =IF(B7=0,0,D7/B7)
A8: セキュリティ | B8: =COUNTIF(キーワード一覧!$B$5:$B$235,A8) | C8: =COUNTIFS(キーワード一覧!$B$5:$B$235,A8,キーワード一覧!$F$5:$F$235,"★★★") | D8: =COUNTIFS(キーワード一覧!$B$5:$B$235,A8,キーワード一覧!$G$5:$G$235,"◎*") | E8: =COUNTIFS(キーワード一覧!$B$5:$B$235,A8,キーワード一覧!$G$5:$G$235,"○*") | F8: =COUNTIFS(キーワード一覧!$B$5:$B$235,A8,キーワード一覧!$G$5:$G$235,"△*") | G8: =IF(B8=0,0,D8/B8)
A9: アプリケーション統合 | B9: =COUNTIF(キーワード一覧!$B$5:$B$235,A9) | C9: =COUNTIFS(キーワード一覧!$B$5:$B$235,A9,キーワード一覧!$F$5:$F$235,"★★★") | D9: =COUNTIFS(キーワード一覧!$B$5:$B$235,A9,キーワード一覧!$G$5:$G$235,"◎*") | E9: =COUNTIFS(キーワード一覧!$B$5:$B$235,A9,キーワード一覧!$G$5:$G$235,"○*") | F9: =COUNTIFS(キーワード一覧!$B$5:$B$235,A9,キーワード一覧!$G$5:$G$235,"△*") | G9: =IF(B9=0,0,D9/B9)
A10: 分析 | B10: =COUNTIF(キーワード一覧!$B$5:$B$235,A10) | C10: =COUNTIFS(キーワード一覧!$B$5:$B$235,A10,キーワード一覧!$F$5:$F$235,"★★★") | D10: =COUNTIFS(キーワード一覧!$B$5:$B$235,A10,キーワード一覧!$G$5:$G$235,"◎*") | E10: =COUNTIFS(キーワード一覧!$B$5:$B$235,A10,キーワード一覧!$G$5:$G$235,"○*") | F10: =COUNTIFS(キーワード一覧!$B$5:$B$235,A10,キーワード一覧!$G$5:$G$235,"△*") | G10: =IF(B10=0,0,D10/B10)
A11: 管理・監視 | B11: =COUNTIF(キーワード一覧!$B$5:$B$235,A11) | C11: =COUNTIFS(キーワード一覧!$B$5:$B$235,A11,キーワード一覧!$F$5:$F$235,"★★★") | D11: =COUNTIFS(キーワード一覧!$B$5:$B$235,A11,キーワード一覧!$G$5:$G$235,"◎*") | E11: =COUNTIFS(キーワード一覧!$B$5:$B$235,A11,キーワード一覧!$G$5:$G$235,"○*") | F11: =COUNTIFS(キーワード一覧!$B$5:$B$235,A11,キーワード一覧!$G$5:$G$235,"△*") | G11: =IF(B11=0,0,D11/B11)
A12: 移行 | B12: =COUNTIF(キーワード一覧!$B$5:$B$235,A12) | C12: =COUNTIFS(キーワード一覧!$B$5:$B$235,A12,キーワード一覧!$F$5:$F$235,"★★★") | D12: =COUNTIFS(キーワード一覧!$B$5:$B$235,A12,キーワード一覧!$G$5:$G$235,"◎*") | E12: =COUNTIFS(キーワード一覧!$B$5:$B$235,A12,キーワード一覧!$G$5:$G$235,"○*") | F12: =COUNTIFS(キーワード一覧!$B$5:$B$235,A12,キーワード一覧!$G$5:$G$235,"△*") | G12: =IF(B12=0,0,D12/B12)
A13: コスト管理 | B13: =COUNTIF(キーワード一覧!$B$5:$B$235,A13) | C13: =COUNTIFS(キーワード一覧!$B$5:$B$235,A13,キーワード一覧!$F$5:$F$235,"★★★") | D13: =COUNTIFS(キーワード一覧!$B$5:$B$235,A13,キーワード一覧!$G$5:$G$235,"◎*") | E13: =COUNTIFS(キーワード一覧!$B$5:$B$235,A13,キーワード一覧!$G$5:$G$235,"○*") | F13: =COUNTIFS(キーワード一覧!$B$5:$B$235,A13,キーワード一覧!$G$5:$G$235,"△*") | G13: =IF(B13=0,0,D13/B13)
A14: AI/ML | B14: =COUNTIF(キーワード一覧!$B$5:$B$235,A14) | C14: =COUNTIFS(キーワード一覧!$B$5:$B$235,A14,キーワード一覧!$F$5:$F$235,"★★★") | D14: =COUNTIFS(キーワード一覧!$B$5:$B$235,A14,キーワード一覧!$G$5:$G$235,"◎*") | E14: =COUNTIFS(キーワード一覧!$B$5:$B$235,A14,キーワード一覧!$G$5:$G$235,"○*") | F14: =COUNTIFS(キーワード一覧!$B$5:$B$235,A14,キーワード一覧!$G$5:$G$235,"△*") | G14: =IF(B14=0,0,D14/B14)
A15: 設計原則 | B15: =COUNTIF(キーワード一覧!$B$5:$B$235,A15) | C15: =COUNTIFS(キーワード一覧!$B$5:$B$235,A15,キーワード一覧!$F$5:$F$235,"★★★") | D15: =COUNTIFS(キーワード一覧!$B$5:$B$235,A15,キーワード一覧!$G$5:$G$235,"◎*") | E15: =COUNTIFS(キーワード一覧!$B$5:$B$235,A15,キーワード一覧!$G$5:$G$235,"○*") | F15: =COUNTIFS(キーワード一覧!$B$5:$B$235,A15,キーワード一覧!$G$5:$G$235,"△*") | G15: =IF(B15=0,0,D15/B15)
A16: 合計 | B16: =SUM(B4:B15) | C16: =SUM(C4:C15) | D16: =SUM(D4:D15) | E16: =SUM(E4:E15) | F16: =SUM(F4:F15) | G16: =IF(B16=0,0,D16/B16)
A18: ※ 数値は「キーワード一覧」シートの分野・重要度・理解度から自動計算されます。
